tcw/__init__.py
tcw/config.py
tcw/database.py
tcw/exc.py
tcw/run.py
tcw/utils.py
tcw/wsgi.py
tcw/apps/__init__.py
tcw/apps/contest/__init__.py
tcw/apps/contest/forms.py
tcw/apps/contest/models.py
tcw/apps/contest/views.py
tcw/apps/contest/templates/__init__.py
tcw/apps/contest/templates/contest/__init__.py
tcw/apps/contest/templates/contest/about.html
tcw/apps/contest/templates/contest/animation.html
tcw/apps/contest/templates/contest/form.html
tcw/apps/contest/templates/contest/index.html
tcw/apps/contest/templates/contest/privacy.html
tcw/apps/contest/templates/contest/signup.html
tcw/apps/contest/templates/contest/slide1.html
tcw/apps/contest/templates/contest/slide2.html
tcw/apps/contest/templates/contest/slide3.html
tcw/apps/contest/templates/contest/sorry.html
tcw/apps/contest/templates/contest/success.html
tcw/apps/contest/templates/contest/thanks.html
tcw/static/__init__.py
tcw/static/images/__init__.py
tcw/templates/404.html
tcw/templates/410.html
tcw/templates/__init__.py
tcw/templates/base.html
tcw-0.1.13.dist-info/LICENSE
tcw-0.1.13.dist-info/METADATA
tcw-0.1.13.dist-info/WHEEL
tcw-0.1.13.dist-info/top_level.txt
tcw-0.1.13.dist-info/RECORD
