Metadata-Version: 2.1
Name: tcw
Version: 0.1.13
Summary: tiny contest winners application
Author: J Leary
Author-email: tinycontestwinners@gmail.com
License-File: LICENSE
Requires-Dist: flask
Requires-Dist: flask-wtf
Requires-Dist: sqlalchemy
Requires-Dist: markdown
